{
  "schemaVersion": "1.0",
  "session": {
    "id": "current",
    "agent": "parallax",
    "agentVersion": "0.2.0",
    "startedAt": "2026-06-01T17:26:48.715Z",
    "endedAt": "2026-06-01T18:13:33.205Z",
    "project": null,
    "projectType": null
  },
  "phases": [
    {
      "phase": "ambiguity_check",
      "timestamp": "2026-06-01T18:05:24.980Z",
      "data": {}
    },
    {
      "phase": "four_invariants",
      "timestamp": "2026-06-01T18:05:34.916Z",
      "data": {}
    },
    {
      "phase": "verification_gate",
      "timestamp": "2026-06-01T18:05:45.342Z",
      "data": {}
    },
    {
      "phase": "design_check",
      "timestamp": "2026-06-01T18:05:55.626Z",
      "data": {}
    },
    {
      "phase": "commit_decision",
      "timestamp": "2026-06-01T18:06:05.087Z",
      "data": {}
    },
    {
      "phase": "summary",
      "timestamp": "2026-06-01T18:06:14.907Z",
      "data": {}
    }
  ],
  "writes": [
    {
      "file": "C:\\Users\\fate\\Desktop\\kanban\\parallax_screencapture\\debug.md",
      "timestamp": "2026-06-01T18:10:19.109Z",
      "verification": "skipped",
      "frictionRetriesLeft": 3
    }
  ],
  "metrics": {
    "durationSeconds": 2804,
    "totalPhases": 6,
    "totalWrites": 1,
    "verificationPassRate": 0,
    "firstAttemptPassRate": 0,
    "totalFrictionRetries": 0,
    "protocolStepsCompleted": 5
  },
  "coherenceScore": null
}